README.rst
setup.py
powershift_cli.egg-info/PKG-INFO
powershift_cli.egg-info/SOURCES.txt
powershift_cli.egg-info/dependency_links.txt
powershift_cli.egg-info/entry_points.txt
powershift_cli.egg-info/requires.txt
powershift_cli.egg-info/top_level.txt
src/powershift/__init__.py
src/powershift/cli/__init__.py
src/powershift/cli/completion-bash.sh