Metadata-Version: 1.1
Name: powershift-cli
Version: 1.2.7
Summary: Pluggable command line client for OpenShift.
Home-page: https://github.com/getwarped/powershift-cli
Author: Graham Dumpleton
Author-email: Graham.Dumpleton@gmail.com
License: BSD
Keywords: openshift kubernetes
Platform: UNKNOWN
Classifier: Development Status :: 4 - Beta
Classifier: License :: OSI Approved :: BSD License
Classifier: Programming Language :: Python :: 2
Classifier: Programming Language :: Python :: 2.7
Classifier: Programming Language :: Python :: 3
Classifier: Programming Language :: Python :: 3.3
Classifier: Programming Language :: Python :: 3.4
Classifier: Programming Language :: Python :: 3.5
Classifier: Programming Language :: Python :: 3.6
